MANIFEST.in
README.rst
setup.cfg
setup.py
collective/__init__.py
collective.pdfpeek.egg-info/PKG-INFO
collective.pdfpeek.egg-info/SOURCES.txt
collective.pdfpeek.egg-info/dependency_links.txt
collective.pdfpeek.egg-info/entry_points.txt
collective.pdfpeek.egg-info/namespace_packages.txt
collective.pdfpeek.egg-info/not-zip-safe
collective.pdfpeek.egg-info/requires.txt
collective.pdfpeek.egg-info/top_level.txt
collective/pdfpeek/__init__.py
collective/pdfpeek/async.py
collective/pdfpeek/configure.zcml
collective/pdfpeek/controlpanel.py
collective/pdfpeek/controlpanel.zcml
collective/pdfpeek/conversion.py
collective/pdfpeek/events.py
collective/pdfpeek/genericsetup.zcml
collective/pdfpeek/interfaces.py
collective/pdfpeek/setuphandlers.py
collective/pdfpeek/testing.py
collective/pdfpeek/traversal.py
collective/pdfpeek/Extensions/Install.py
collective/pdfpeek/at/__init__.py
collective/pdfpeek/at/configure.zcml
collective/pdfpeek/at/conversion.py
collective/pdfpeek/at/profiles/default/metadata.xml
collective/pdfpeek/browser/__init__.py
collective/pdfpeek/browser/configure.zcml
collective/pdfpeek/browser/interfaces.py
collective/pdfpeek/browser/pdf.py
collective/pdfpeek/browser/utils.py
collective/pdfpeek/browser/viewlets.py
collective/pdfpeek/browser/images/black.png
collective/pdfpeek/browser/images/black_arrow.png
collective/pdfpeek/browser/images/close.png
collective/pdfpeek/browser/images/h150.png
collective/pdfpeek/browser/images/h300.png
collective/pdfpeek/browser/images/h80.png
collective/pdfpeek/browser/images/hori_large.png
collective/pdfpeek/browser/images/loading.gif
collective/pdfpeek/browser/images/mask_gradient_1800.png
collective/pdfpeek/browser/images/pdfpeek_icon.png
collective/pdfpeek/browser/images/vert_large.png
collective/pdfpeek/browser/javascript/jquery.reflect.js
collective/pdfpeek/browser/stylesheets/pdfpeek.css
collective/pdfpeek/browser/templates/pdfpeek.pt
collective/pdfpeek/dx/__init__.py
collective/pdfpeek/dx/behaviors.py
collective/pdfpeek/dx/configure.zcml
collective/pdfpeek/dx/conversion.py
collective/pdfpeek/dx/profiles/default/metadata.xml
collective/pdfpeek/dx/profiles/default/types.xml
collective/pdfpeek/dx/profiles/default/types/file.xml
collective/pdfpeek/profiles/default/browserlayer.xml
collective/pdfpeek/profiles/default/collective.pdfpeek_various.txt
