Metadata-Version: 1.1
Name: collective.pdfpeek
Version: 2.0.0
Summary: A Plone 4 product that generates image thumbnail previews of PDF files stored on ATFile based objects.
Home-page: https://github.com/collective/collective.pdfpeek
Author: David Brenneman
Author-email: db@davidbrenneman.com
License: GPL
Keywords: Plone Zope Python PDF
Platform: UNKNOWN
Classifier: Framework :: Plone
Classifier: Programming Language :: Python
Classifier: Topic :: Software Development :: Libraries :: Python Modules
